mm_mongo/__init__.py
mm_mongo/async_collection.py
mm_mongo/collection.py
mm_mongo/connection.py
mm_mongo/errors.py
mm_mongo/model.py
mm_mongo/py.typed
mm_mongo/pydantic.py
mm_mongo/types.py
mm_mongo/utils.py
mm_mongo-0.6.3.dist-info/METADATA
mm_mongo-0.6.3.dist-info/WHEEL
mm_mongo-0.6.3.dist-info/RECORD
