Metadata-Version: 2.4
Name: mm-mongo
Version: 0.6.3
Summary: Type-safe PyMongo wrapper with Pydantic integration
Requires-Python: >=3.13
Requires-Dist: pydantic~=2.12.5
Requires-Dist: pymongo~=4.16.0
